{
  "asOf": "2026-07-08",
  "entryDateUsed": "2025-07-28",
  "valuationDate": "2026-07-07",
  "initialCapitalUsd": 8000.0,
  "aumUsd": 10118.13,
  "positions": [
    {
      "ticker": "AAPL",
      "shares": 1.87613571,
      "entryPrice": 213.2042,
      "currentPrice": 310.66,
      "entryValue": 400.0,
      "marketValue": 582.84,
      "currentWeight": 0.057604,
      "pnlUsd": 182.84,
      "returnPct": 45.71
    },
    {
      "ticker": "AMZN",
      "shares": 1.54645823,
      "entryPrice": 232.79,
      "currentPrice": 245.98,
      "entryValue": 360.0,
      "marketValue": 380.4,
      "currentWeight": 0.037596,
      "pnlUsd": 20.4,
      "returnPct": 5.666
    },
    {
      "ticker": "MSFT",
      "shares": 0.94406635,
      "entryPrice": 508.4388,
      "currentPrice": 388.84,
      "entryValue": 480.0,
      "marketValue": 367.09,
      "currentWeight": 0.036281,
      "pnlUsd": -112.91,
      "returnPct": -23.523
    },
    {
      "ticker": "GOOGL",
      "shares": 2.08298421,
      "entryPrice": 192.0322,
      "currentPrice": 367.03,
      "entryValue": 400.0,
      "marketValue": 764.52,
      "currentWeight": 0.075559,
      "pnlUsd": 364.52,
      "returnPct": 91.129
    },
    {
      "ticker": "NVDA",
      "shares": 2.71615152,
      "entryPrice": 176.7206,
      "currentPrice": 196.93,
      "entryValue": 480.0,
      "marketValue": 534.89,
      "currentWeight": 0.052865,
      "pnlUsd": 54.89,
      "returnPct": 11.436
    },
    {
      "ticker": "META",
      "shares": 0.67106058,
      "entryPrice": 715.2856,
      "currentPrice": 615.58,
      "entryValue": 480.0,
      "marketValue": 413.09,
      "currentWeight": 0.040827,
      "pnlUsd": -66.91,
      "returnPct": -13.939
    },
    {
      "ticker": "PANW",
      "shares": 1.56479218,
      "entryPrice": 204.5,
      "currentPrice": 337.04,
      "entryValue": 320.0,
      "marketValue": 527.4,
      "currentWeight": 0.052124,
      "pnlUsd": 207.4,
      "returnPct": 64.812
    },
    {
      "ticker": "AVGO",
      "shares": 1.09529287,
      "entryPrice": 292.1593,
      "currentPrice": 370.78,
      "entryValue": 320.0,
      "marketValue": 406.11,
      "currentWeight": 0.040137,
      "pnlUsd": 86.11,
      "returnPct": 26.91
    },
    {
      "ticker": "PLTR",
      "shares": 2.53356972,
      "entryPrice": 157.88,
      "currentPrice": 134.37,
      "entryValue": 400.0,
      "marketValue": 340.44,
      "currentWeight": 0.033646,
      "pnlUsd": -59.56,
      "returnPct": -14.891
    },
    {
      "ticker": "TSM",
      "shares": 1.66600942,
      "entryPrice": 240.0947,
      "currentPrice": 432.57,
      "entryValue": 400.0,
      "marketValue": 720.67,
      "currentWeight": 0.071225,
      "pnlUsd": 320.67,
      "returnPct": 80.166
    },
    {
      "ticker": "AMD",
      "shares": 2.07301619,
      "entryPrice": 173.66,
      "currentPrice": 516.11,
      "entryValue": 360.0,
      "marketValue": 1069.9,
      "currentWeight": 0.105741,
      "pnlUsd": 709.9,
      "returnPct": 197.196
    },
    {
      "ticker": "CRWV",
      "shares": 3.26441788,
      "entryPrice": 110.28,
      "currentPrice": 83.53,
      "entryValue": 360.0,
      "marketValue": 272.68,
      "currentWeight": 0.026949,
      "pnlUsd": -87.32,
      "returnPct": -24.256
    },
    {
      "ticker": "ZS",
      "shares": 0.83033488,
      "entryPrice": 289.04,
      "currentPrice": 149.5,
      "entryValue": 240.0,
      "marketValue": 124.14,
      "currentWeight": 0.012269,
      "pnlUsd": -115.86,
      "returnPct": -48.277
    },
    {
      "ticker": "CRM",
      "shares": 1.04484691,
      "entryPrice": 267.9818,
      "currentPrice": 169.52,
      "entryValue": 280.0,
      "marketValue": 177.12,
      "currentWeight": 0.017505,
      "pnlUsd": -102.88,
      "returnPct": -36.742
    },
    {
      "ticker": "GFS",
      "shares": 7.87760953,
      "entryPrice": 40.6215,
      "currentPrice": 65.84,
      "entryValue": 320.0,
      "marketValue": 518.66,
      "currentWeight": 0.051261,
      "pnlUsd": 198.66,
      "returnPct": 62.082
    },
    {
      "ticker": "RTX",
      "shares": 2.60379926,
      "entryPrice": 153.6217,
      "currentPrice": 200.85,
      "entryValue": 400.0,
      "marketValue": 522.97,
      "currentWeight": 0.051687,
      "pnlUsd": 122.97,
      "returnPct": 30.743
    },
    {
      "ticker": "LMT",
      "shares": 0.58116989,
      "entryPrice": 412.9601,
      "currentPrice": 535.38,
      "entryValue": 240.0,
      "marketValue": 311.15,
      "currentWeight": 0.030751,
      "pnlUsd": 71.15,
      "returnPct": 29.644
    },
    {
      "ticker": "BA",
      "shares": 0.67679031,
      "entryPrice": 236.41,
      "currentPrice": 231.68,
      "entryValue": 160.0,
      "marketValue": 156.8,
      "currentWeight": 0.015497,
      "pnlUsd": -3.2,
      "returnPct": -2.001
    },
    {
      "ticker": "NOC",
      "shares": 0.3556779,
      "entryPrice": 562.3065,
      "currentPrice": 549.04,
      "entryValue": 200.0,
      "marketValue": 195.28,
      "currentWeight": 0.0193,
      "pnlUsd": -4.72,
      "returnPct": -2.359
    },
    {
      "ticker": "GD",
      "shares": 0.78005118,
      "entryPrice": 307.6721,
      "currentPrice": 374.64,
      "entryValue": 240.0,
      "marketValue": 292.24,
      "currentWeight": 0.028883,
      "pnlUsd": 52.24,
      "returnPct": 21.766
    },
    {
      "ticker": "HII",
      "shares": 0.92976098,
      "entryPrice": 258.1309,
      "currentPrice": 289.46,
      "entryValue": 240.0,
      "marketValue": 269.13,
      "currentWeight": 0.026599,
      "pnlUsd": 29.13,
      "returnPct": 12.137
    },
    {
      "ticker": "LHX",
      "shares": 0.75118619,
      "entryPrice": 266.2456,
      "currentPrice": 295.4,
      "entryValue": 200.0,
      "marketValue": 221.9,
      "currentWeight": 0.021931,
      "pnlUsd": 21.9,
      "returnPct": 10.95
    },
    {
      "ticker": "LDOS",
      "shares": 1.51244762,
      "entryPrice": 158.6832,
      "currentPrice": 108.57,
      "entryValue": 240.0,
      "marketValue": 164.21,
      "currentWeight": 0.016229,
      "pnlUsd": -75.79,
      "returnPct": -31.581
    },
    {
      "ticker": "CACI",
      "shares": 0.51795582,
      "entryPrice": 463.36,
      "currentPrice": 497.36,
      "entryValue": 240.0,
      "marketValue": 257.61,
      "currentWeight": 0.02546,
      "pnlUsd": 17.61,
      "returnPct": 7.338
    },
    {
      "ticker": "MRCY",
      "shares": 4.54890083,
      "entryPrice": 52.76,
      "currentPrice": 115.83,
      "entryValue": 240.0,
      "marketValue": 526.9,
      "currentWeight": 0.052075,
      "pnlUsd": 286.9,
      "returnPct": 119.541
    }
  ],
  "missingTickersDropped": [],
  "weightsRenormalized": false
}