{
  "asOf": "2026-05-08",
  "entryDateUsed": "2025-07-28",
  "valuationDate": "2026-05-07",
  "initialCapitalUsd": 8000.0,
  "aumUsd": 9156.62,
  "positions": [
    {
      "ticker": "AAPL",
      "shares": 1.8744088,
      "entryPrice": 213.4006,
      "currentPrice": 287.44,
      "entryValue": 400.0,
      "marketValue": 538.78,
      "currentWeight": NaN,
      "pnlUsd": 138.78,
      "returnPct": 34.695
    },
    {
      "ticker": "AMZN",
      "shares": 1.54645823,
      "entryPrice": 232.79,
      "currentPrice": 271.17,
      "entryValue": 360.0,
      "marketValue": 419.35,
      "currentWeight": NaN,
      "pnlUsd": 59.35,
      "returnPct": 16.487
    },
    {
      "ticker": "MSFT",
      "shares": 0.94202607,
      "entryPrice": 509.54,
      "currentPrice": 420.77,
      "entryValue": 480.0,
      "marketValue": 396.38,
      "currentWeight": NaN,
      "pnlUsd": -83.62,
      "returnPct": -17.422
    },
    {
      "ticker": "GOOGL",
      "shares": 2.08174079,
      "entryPrice": 192.1469,
      "currentPrice": 397.99,
      "entryValue": 400.0,
      "marketValue": 828.51,
      "currentWeight": NaN,
      "pnlUsd": 428.51,
      "returnPct": 107.128
    },
    {
      "ticker": "NVDA",
      "shares": 2.71615152,
      "entryPrice": 176.7206,
      "currentPrice": 211.5,
      "entryValue": 480.0,
      "marketValue": 574.47,
      "currentWeight": NaN,
      "pnlUsd": 94.47,
      "returnPct": 19.68
    },
    {
      "ticker": "META",
      "shares": 0.66986566,
      "entryPrice": 716.5616,
      "currentPrice": 616.81,
      "entryValue": 480.0,
      "marketValue": 413.18,
      "currentWeight": NaN,
      "pnlUsd": -66.82,
      "returnPct": -13.921
    },
    {
      "ticker": "PANW",
      "shares": 1.56479218,
      "entryPrice": 204.5,
      "currentPrice": 196.53,
      "entryValue": 320.0,
      "marketValue": 307.53,
      "currentWeight": NaN,
      "pnlUsd": -12.47,
      "returnPct": -3.897
    },
    {
      "ticker": "AVGO",
      "shares": 1.09127293,
      "entryPrice": 293.2355,
      "currentPrice": 412.56,
      "entryValue": 320.0,
      "marketValue": 450.22,
      "currentWeight": NaN,
      "pnlUsd": 130.22,
      "returnPct": 40.692
    },
    {
      "ticker": "PLTR",
      "shares": 2.53356972,
      "entryPrice": 157.88,
      "currentPrice": 137.05,
      "entryValue": 400.0,
      "marketValue": 347.23,
      "currentWeight": NaN,
      "pnlUsd": -52.77,
      "returnPct": -13.194
    },
    {
      "ticker": "TSM",
      "shares": 1.65744655,
      "entryPrice": 241.3351,
      "currentPrice": 414.15,
      "entryValue": 400.0,
      "marketValue": 686.43,
      "currentWeight": NaN,
      "pnlUsd": 286.43,
      "returnPct": 71.608
    },
    {
      "ticker": "AMD",
      "shares": 2.07301619,
      "entryPrice": 173.66,
      "currentPrice": 408.46,
      "entryValue": 360.0,
      "marketValue": 846.74,
      "currentWeight": NaN,
      "pnlUsd": 486.74,
      "returnPct": 135.207
    },
    {
      "ticker": "CRWV",
      "shares": 3.26441788,
      "entryPrice": 110.28,
      "currentPrice": 128.84,
      "entryValue": 360.0,
      "marketValue": 420.59,
      "currentWeight": NaN,
      "pnlUsd": 60.59,
      "returnPct": 16.83
    },
    {
      "ticker": "ZS",
      "shares": 0.83033488,
      "entryPrice": 289.04,
      "currentPrice": 152.79,
      "entryValue": 240.0,
      "marketValue": 126.87,
      "currentWeight": NaN,
      "pnlUsd": -113.13,
      "returnPct": -47.139
    },
    {
      "ticker": "CRM",
      "shares": 1.03955716,
      "entryPrice": 269.3455,
      "currentPrice": 186.34,
      "entryValue": 280.0,
      "marketValue": 193.71,
      "currentWeight": NaN,
      "pnlUsd": -86.29,
      "returnPct": -30.817
    },
    {
      "ticker": "GFS",
      "shares": 7.86627329,
      "entryPrice": 40.68,
      "currentPrice": 70.93,
      "entryValue": 320.0,
      "marketValue": 557.95,
      "currentWeight": NaN,
      "pnlUsd": 237.95,
      "returnPct": 74.361
    },
    {
      "ticker": "RTX",
      "shares": 2.59299844,
      "entryPrice": 154.2616,
      "currentPrice": 176.78,
      "entryValue": 400.0,
      "marketValue": 458.39,
      "currentWeight": NaN,
      "pnlUsd": 58.39,
      "returnPct": 14.598
    },
    {
      "ticker": "LMT",
      "shares": 0.58116989,
      "entryPrice": 412.9601,
      "currentPrice": NaN,
      "entryValue": 240.0,
      "marketValue": NaN,
      "currentWeight": NaN,
      "pnlUsd": NaN,
      "returnPct": NaN
    },
    {
      "ticker": "BA",
      "shares": 0.67679031,
      "entryPrice": 236.41,
      "currentPrice": 231.03,
      "entryValue": 160.0,
      "marketValue": 156.36,
      "currentWeight": NaN,
      "pnlUsd": -3.64,
      "returnPct": -2.276
    },
    {
      "ticker": "NOC",
      "shares": 0.3556779,
      "entryPrice": 562.3065,
      "currentPrice": 552.27,
      "entryValue": 200.0,
      "marketValue": 196.43,
      "currentWeight": NaN,
      "pnlUsd": -3.57,
      "returnPct": -1.785
    },
    {
      "ticker": "GD",
      "shares": 0.77304252,
      "entryPrice": 310.4616,
      "currentPrice": 347.76,
      "entryValue": 240.0,
      "marketValue": 268.83,
      "currentWeight": NaN,
      "pnlUsd": 28.83,
      "returnPct": 12.014
    },
    {
      "ticker": "HII",
      "shares": 0.92576271,
      "entryPrice": 259.2457,
      "currentPrice": 314.72,
      "entryValue": 240.0,
      "marketValue": 291.36,
      "currentWeight": NaN,
      "pnlUsd": 51.36,
      "returnPct": 21.398
    },
    {
      "ticker": "LHX",
      "shares": 0.75118628,
      "entryPrice": 266.2455,
      "currentPrice": 301.18,
      "entryValue": 200.0,
      "marketValue": 226.24,
      "currentWeight": NaN,
      "pnlUsd": 26.24,
      "returnPct": 13.121
    },
    {
      "ticker": "LDOS",
      "shares": 1.50339656,
      "entryPrice": 159.6385,
      "currentPrice": 131.26,
      "entryValue": 240.0,
      "marketValue": 197.34,
      "currentWeight": NaN,
      "pnlUsd": -42.66,
      "returnPct": -17.777
    },
    {
      "ticker": "CACI",
      "shares": 0.51795582,
      "entryPrice": 463.36,
      "currentPrice": 489.88,
      "entryValue": 240.0,
      "marketValue": 253.74,
      "currentWeight": NaN,
      "pnlUsd": 13.74,
      "returnPct": 5.723
    },
    {
      "ticker": "MRCY",
      "shares": 4.54890083,
      "entryPrice": 52.76,
      "currentPrice": NaN,
      "entryValue": 240.0,
      "marketValue": NaN,
      "currentWeight": NaN,
      "pnlUsd": NaN,
      "returnPct": NaN
    }
  ],
  "missingTickersDropped": [],
  "weightsRenormalized": false
}