{
  "asOf": "2026-06-26",
  "entryDateUsed": "2025-07-28",
  "valuationDate": "2026-06-25",
  "initialCapitalUsd": 8000.0,
  "aumUsd": 9741.94,
  "positions": [
    {
      "ticker": "AAPL",
      "shares": 1.8744088,
      "entryPrice": 213.4006,
      "currentPrice": 275.15,
      "entryValue": 400.0,
      "marketValue": 515.74,
      "currentWeight": 0.052941,
      "pnlUsd": 115.74,
      "returnPct": 28.936
    },
    {
      "ticker": "AMZN",
      "shares": 1.54645823,
      "entryPrice": 232.79,
      "currentPrice": 227.01,
      "entryValue": 360.0,
      "marketValue": 351.06,
      "currentWeight": 0.036036,
      "pnlUsd": -8.94,
      "returnPct": -2.483
    },
    {
      "ticker": "MSFT",
      "shares": 0.94202607,
      "entryPrice": 509.54,
      "currentPrice": 352.83,
      "entryValue": 480.0,
      "marketValue": 332.38,
      "currentWeight": 0.034118,
      "pnlUsd": -147.62,
      "returnPct": -30.755
    },
    {
      "ticker": "GOOGL",
      "shares": 2.08174079,
      "entryPrice": 192.1469,
      "currentPrice": 343.71,
      "entryValue": 400.0,
      "marketValue": 715.52,
      "currentWeight": 0.073447,
      "pnlUsd": 315.52,
      "returnPct": 78.879
    },
    {
      "ticker": "NVDA",
      "shares": 2.71615152,
      "entryPrice": 176.7206,
      "currentPrice": 195.74,
      "entryValue": 480.0,
      "marketValue": 531.66,
      "currentWeight": 0.054574,
      "pnlUsd": 51.66,
      "returnPct": 10.762
    },
    {
      "ticker": "META",
      "shares": 0.66986566,
      "entryPrice": 716.5616,
      "currentPrice": 542.87,
      "entryValue": 480.0,
      "marketValue": 363.65,
      "currentWeight": 0.037328,
      "pnlUsd": -116.35,
      "returnPct": -24.24
    },
    {
      "ticker": "PANW",
      "shares": 1.56479218,
      "entryPrice": 204.5,
      "currentPrice": 293.09,
      "entryValue": 320.0,
      "marketValue": 458.62,
      "currentWeight": 0.047077,
      "pnlUsd": 138.62,
      "returnPct": 43.32
    },
    {
      "ticker": "AVGO",
      "shares": 1.09127293,
      "entryPrice": 293.2355,
      "currentPrice": 378.91,
      "entryValue": 320.0,
      "marketValue": 413.49,
      "currentWeight": 0.042445,
      "pnlUsd": 93.49,
      "returnPct": 29.217
    },
    {
      "ticker": "PLTR",
      "shares": 2.53356972,
      "entryPrice": 157.88,
      "currentPrice": 107.27,
      "entryValue": 400.0,
      "marketValue": 271.78,
      "currentWeight": 0.027898,
      "pnlUsd": -128.22,
      "returnPct": -32.056
    },
    {
      "ticker": "TSM",
      "shares": 1.65744655,
      "entryPrice": 241.3351,
      "currentPrice": 434.99,
      "entryValue": 400.0,
      "marketValue": 720.97,
      "currentWeight": 0.074007,
      "pnlUsd": 320.97,
      "returnPct": 80.243
    },
    {
      "ticker": "AMD",
      "shares": 2.07301619,
      "entryPrice": 173.66,
      "currentPrice": 532.57,
      "entryValue": 360.0,
      "marketValue": 1104.03,
      "currentWeight": 0.113327,
      "pnlUsd": 744.03,
      "returnPct": 206.674
    },
    {
      "ticker": "CRWV",
      "shares": 3.26441788,
      "entryPrice": 110.28,
      "currentPrice": 98.76,
      "entryValue": 360.0,
      "marketValue": 322.39,
      "currentWeight": 0.033093,
      "pnlUsd": -37.61,
      "returnPct": -10.446
    },
    {
      "ticker": "ZS",
      "shares": 0.83033488,
      "entryPrice": 289.04,
      "currentPrice": 123.8,
      "entryValue": 240.0,
      "marketValue": 102.8,
      "currentWeight": 0.010552,
      "pnlUsd": -137.2,
      "returnPct": -57.169
    },
    {
      "ticker": "CRM",
      "shares": 1.03955716,
      "entryPrice": 269.3455,
      "currentPrice": 150.19,
      "entryValue": 280.0,
      "marketValue": 156.13,
      "currentWeight": 0.016027,
      "pnlUsd": -123.87,
      "returnPct": -44.239
    },
    {
      "ticker": "GFS",
      "shares": 7.86627329,
      "entryPrice": 40.68,
      "currentPrice": 86.12,
      "entryValue": 320.0,
      "marketValue": 677.44,
      "currentWeight": 0.069539,
      "pnlUsd": 357.44,
      "returnPct": 111.701
    },
    {
      "ticker": "RTX",
      "shares": 2.59299844,
      "entryPrice": 154.2616,
      "currentPrice": 186.59,
      "entryValue": 400.0,
      "marketValue": 483.83,
      "currentWeight": 0.049664,
      "pnlUsd": 83.83,
      "returnPct": 20.957
    },
    {
      "ticker": "LMT",
      "shares": 0.58116989,
      "entryPrice": 412.9601,
      "currentPrice": 505.02,
      "entryValue": 240.0,
      "marketValue": 293.5,
      "currentWeight": 0.030128,
      "pnlUsd": 53.5,
      "returnPct": 22.293
    },
    {
      "ticker": "BA",
      "shares": 0.67679031,
      "entryPrice": 236.41,
      "currentPrice": 218.12,
      "entryValue": 160.0,
      "marketValue": 147.62,
      "currentWeight": 0.015153,
      "pnlUsd": -12.38,
      "returnPct": -7.737
    },
    {
      "ticker": "NOC",
      "shares": 0.3556779,
      "entryPrice": 562.3065,
      "currentPrice": 499.33,
      "entryValue": 200.0,
      "marketValue": 177.6,
      "currentWeight": 0.018231,
      "pnlUsd": -22.4,
      "returnPct": -11.2
    },
    {
      "ticker": "GD",
      "shares": 0.77304252,
      "entryPrice": 310.4616,
      "currentPrice": 344.7,
      "entryValue": 240.0,
      "marketValue": 266.47,
      "currentWeight": 0.027353,
      "pnlUsd": 26.47,
      "returnPct": 11.028
    },
    {
      "ticker": "HII",
      "shares": 0.92576271,
      "entryPrice": 259.2457,
      "currentPrice": 279.09,
      "entryValue": 240.0,
      "marketValue": 258.37,
      "currentWeight": 0.026522,
      "pnlUsd": 18.37,
      "returnPct": 7.655
    },
    {
      "ticker": "LHX",
      "shares": 0.75118628,
      "entryPrice": 266.2455,
      "currentPrice": 288.52,
      "entryValue": 200.0,
      "marketValue": 216.73,
      "currentWeight": 0.022247,
      "pnlUsd": 16.73,
      "returnPct": 8.366
    },
    {
      "ticker": "LDOS",
      "shares": 1.50339656,
      "entryPrice": 159.6385,
      "currentPrice": 100.0,
      "entryValue": 240.0,
      "marketValue": 150.34,
      "currentWeight": 0.015432,
      "pnlUsd": -89.66,
      "returnPct": -37.358
    },
    {
      "ticker": "CACI",
      "shares": 0.51795582,
      "entryPrice": 463.36,
      "currentPrice": 443.26,
      "entryValue": 240.0,
      "marketValue": 229.59,
      "currentWeight": 0.023567,
      "pnlUsd": -10.41,
      "returnPct": -4.338
    },
    {
      "ticker": "MRCY",
      "shares": 4.54890083,
      "entryPrice": 52.76,
      "currentPrice": 105.57,
      "entryValue": 240.0,
      "marketValue": 480.23,
      "currentWeight": 0.049295,
      "pnlUsd": 240.23,
      "returnPct": 100.095
    }
  ],
  "missingTickersDropped": [],
  "weightsRenormalized": false
}