{
  "asOf": "2026-06-22",
  "entryDateUsed": "2025-07-28",
  "valuationDate": "2026-06-22",
  "initialCapitalUsd": 8000.0,
  "aumUsd": 10100.96,
  "positions": [
    {
      "ticker": "AAPL",
      "shares": 1.87613571,
      "entryPrice": 213.2042,
      "currentPrice": 299.81,
      "entryValue": 400.0,
      "marketValue": 562.48,
      "currentWeight": 0.055686,
      "pnlUsd": 162.48,
      "returnPct": 40.621
    },
    {
      "ticker": "AMZN",
      "shares": 1.54645823,
      "entryPrice": 232.79,
      "currentPrice": 233.15,
      "entryValue": 360.0,
      "marketValue": 360.56,
      "currentWeight": 0.035695,
      "pnlUsd": 0.56,
      "returnPct": 0.155
    },
    {
      "ticker": "MSFT",
      "shares": 0.9440664,
      "entryPrice": 508.4388,
      "currentPrice": 371.065,
      "entryValue": 480.0,
      "marketValue": 350.31,
      "currentWeight": 0.034681,
      "pnlUsd": -129.69,
      "returnPct": -27.019
    },
    {
      "ticker": "GOOGL",
      "shares": 2.08298421,
      "entryPrice": 192.0322,
      "currentPrice": 345.0,
      "entryValue": 400.0,
      "marketValue": 718.63,
      "currentWeight": 0.071145,
      "pnlUsd": 318.63,
      "returnPct": 79.657
    },
    {
      "ticker": "NVDA",
      "shares": 2.71931706,
      "entryPrice": 176.5149,
      "currentPrice": 210.17,
      "entryValue": 480.0,
      "marketValue": 571.52,
      "currentWeight": 0.056581,
      "pnlUsd": 91.52,
      "returnPct": 19.066
    },
    {
      "ticker": "META",
      "shares": 0.67106058,
      "entryPrice": 715.2856,
      "currentPrice": 560.615,
      "entryValue": 480.0,
      "marketValue": 376.21,
      "currentWeight": 0.037245,
      "pnlUsd": -103.79,
      "returnPct": -21.624
    },
    {
      "ticker": "PANW",
      "shares": 1.56479218,
      "entryPrice": 204.5,
      "currentPrice": 289.515,
      "entryValue": 320.0,
      "marketValue": 453.03,
      "currentWeight": 0.04485,
      "pnlUsd": 133.03,
      "returnPct": 41.572
    },
    {
      "ticker": "AVGO",
      "shares": 1.09356208,
      "entryPrice": 292.6217,
      "currentPrice": 395.48,
      "entryValue": 320.0,
      "marketValue": 432.48,
      "currentWeight": 0.042816,
      "pnlUsd": 112.48,
      "returnPct": 35.151
    },
    {
      "ticker": "PLTR",
      "shares": 2.53356972,
      "entryPrice": 157.88,
      "currentPrice": 122.86,
      "entryValue": 400.0,
      "marketValue": 311.27,
      "currentWeight": 0.030816,
      "pnlUsd": -88.73,
      "returnPct": -22.181
    },
    {
      "ticker": "TSM",
      "shares": 1.66600942,
      "entryPrice": 240.0947,
      "currentPrice": 467.98,
      "entryValue": 400.0,
      "marketValue": 779.66,
      "currentWeight": 0.077187,
      "pnlUsd": 379.66,
      "returnPct": 94.915
    },
    {
      "ticker": "AMD",
      "shares": 2.07301619,
      "entryPrice": 173.66,
      "currentPrice": 544.655,
      "entryValue": 360.0,
      "marketValue": 1129.08,
      "currentWeight": 0.111779,
      "pnlUsd": 769.08,
      "returnPct": 213.633
    },
    {
      "ticker": "CRWV",
      "shares": 3.26441788,
      "entryPrice": 110.28,
      "currentPrice": 110.0,
      "entryValue": 360.0,
      "marketValue": 359.09,
      "currentWeight": 0.03555,
      "pnlUsd": -0.91,
      "returnPct": -0.254
    },
    {
      "ticker": "ZS",
      "shares": 0.83033488,
      "entryPrice": 289.04,
      "currentPrice": 124.225,
      "entryValue": 240.0,
      "marketValue": 103.15,
      "currentWeight": 0.010212,
      "pnlUsd": -136.85,
      "returnPct": -57.022
    },
    {
      "ticker": "CRM",
      "shares": 1.04484679,
      "entryPrice": 267.9819,
      "currentPrice": 148.9099,
      "entryValue": 280.0,
      "marketValue": 155.59,
      "currentWeight": 0.015403,
      "pnlUsd": -124.41,
      "returnPct": -44.433
    },
    {
      "ticker": "GFS",
      "shares": 7.86627329,
      "entryPrice": 40.68,
      "currentPrice": 89.32,
      "entryValue": 320.0,
      "marketValue": 702.62,
      "currentWeight": 0.069559,
      "pnlUsd": 382.62,
      "returnPct": 119.567
    },
    {
      "ticker": "RTX",
      "shares": 2.603799,
      "entryPrice": 153.6217,
      "currentPrice": 182.26,
      "entryValue": 400.0,
      "marketValue": 474.57,
      "currentWeight": 0.046982,
      "pnlUsd": 74.57,
      "returnPct": 18.642
    },
    {
      "ticker": "LMT",
      "shares": 0.58497446,
      "entryPrice": 410.2743,
      "currentPrice": 495.4808,
      "entryValue": 240.0,
      "marketValue": 289.84,
      "currentWeight": 0.028695,
      "pnlUsd": 49.84,
      "returnPct": 20.768
    },
    {
      "ticker": "BA",
      "shares": 0.67679031,
      "entryPrice": 236.41,
      "currentPrice": 221.45,
      "entryValue": 160.0,
      "marketValue": 149.88,
      "currentWeight": 0.014838,
      "pnlUsd": -10.12,
      "returnPct": -6.328
    },
    {
      "ticker": "NOC",
      "shares": 0.35724331,
      "entryPrice": 559.8425,
      "currentPrice": 507.115,
      "entryValue": 200.0,
      "marketValue": 181.16,
      "currentWeight": 0.017935,
      "pnlUsd": -18.84,
      "returnPct": -9.418
    },
    {
      "ticker": "GD",
      "shares": 0.77663314,
      "entryPrice": 309.0262,
      "currentPrice": 344.9651,
      "entryValue": 240.0,
      "marketValue": 267.91,
      "currentWeight": 0.026523,
      "pnlUsd": 27.91,
      "returnPct": 11.63
    },
    {
      "ticker": "HII",
      "shares": 0.92976098,
      "entryPrice": 258.1309,
      "currentPrice": 278.215,
      "entryValue": 240.0,
      "marketValue": 258.67,
      "currentWeight": 0.025609,
      "pnlUsd": 18.67,
      "returnPct": 7.781
    },
    {
      "ticker": "LHX",
      "shares": 0.75422962,
      "entryPrice": 265.1712,
      "currentPrice": 286.15,
      "entryValue": 200.0,
      "marketValue": 215.82,
      "currentWeight": 0.021367,
      "pnlUsd": 15.82,
      "returnPct": 7.911
    },
    {
      "ticker": "LDOS",
      "shares": 1.51244776,
      "entryPrice": 158.6832,
      "currentPrice": 103.66,
      "entryValue": 240.0,
      "marketValue": 156.78,
      "currentWeight": 0.015521,
      "pnlUsd": -83.22,
      "returnPct": -34.675
    },
    {
      "ticker": "CACI",
      "shares": 0.51795582,
      "entryPrice": 463.36,
      "currentPrice": 448.79,
      "entryValue": 240.0,
      "marketValue": 232.45,
      "currentWeight": 0.023013,
      "pnlUsd": -7.55,
      "returnPct": -3.144
    },
    {
      "ticker": "MRCY",
      "shares": 4.54890083,
      "entryPrice": 52.76,
      "currentPrice": 111.72,
      "entryValue": 240.0,
      "marketValue": 508.2,
      "currentWeight": 0.050312,
      "pnlUsd": 268.2,
      "returnPct": 111.751
    }
  ],
  "missingTickersDropped": [],
  "weightsRenormalized": false
}