{
  "asOf": "2026-02-20",
  "entryDateUsed": "2025-07-28",
  "valuationDate": "2026-02-19",
  "initialCapitalUsd": 8000.0,
  "aumUsd": 8987.91,
  "positions": [
    {
      "ticker": "AAPL",
      "shares": 1.8744088,
      "entryPrice": 213.4006,
      "currentPrice": 260.58,
      "entryValue": 400.0,
      "marketValue": 488.43,
      "currentWeight": 0.054343,
      "pnlUsd": 88.43,
      "returnPct": 22.108
    },
    {
      "ticker": "AMZN",
      "shares": 1.54645823,
      "entryPrice": 232.79,
      "currentPrice": 204.86,
      "entryValue": 360.0,
      "marketValue": 316.81,
      "currentWeight": 0.035248,
      "pnlUsd": -43.19,
      "returnPct": -11.998
    },
    {
      "ticker": "MSFT",
      "shares": 0.93988085,
      "entryPrice": 510.703,
      "currentPrice": 398.46,
      "entryValue": 480.0,
      "marketValue": 374.5,
      "currentWeight": 0.041668,
      "pnlUsd": -105.5,
      "returnPct": -21.978
    },
    {
      "ticker": "GOOGL",
      "shares": 2.08027646,
      "entryPrice": 192.2821,
      "currentPrice": 302.85,
      "entryValue": 400.0,
      "marketValue": 630.01,
      "currentWeight": 0.070095,
      "pnlUsd": 230.01,
      "returnPct": 57.503
    },
    {
      "ticker": "NVDA",
      "shares": 2.71600449,
      "entryPrice": 176.7302,
      "currentPrice": 187.9,
      "entryValue": 480.0,
      "marketValue": 510.34,
      "currentWeight": 0.05678,
      "pnlUsd": 30.34,
      "returnPct": 6.32
    },
    {
      "ticker": "META",
      "shares": 0.66986566,
      "entryPrice": 716.5616,
      "currentPrice": 644.78,
      "entryValue": 480.0,
      "marketValue": 431.92,
      "currentWeight": 0.048055,
      "pnlUsd": -48.08,
      "returnPct": -10.017
    },
    {
      "ticker": "PANW",
      "shares": 1.56479218,
      "entryPrice": 204.5,
      "currentPrice": 150.99,
      "entryValue": 320.0,
      "marketValue": 236.27,
      "currentWeight": 0.026287,
      "pnlUsd": -83.73,
      "returnPct": -26.166
    },
    {
      "ticker": "AVGO",
      "shares": 1.09127293,
      "entryPrice": 293.2355,
      "currentPrice": 333.99,
      "entryValue": 320.0,
      "marketValue": 364.47,
      "currentWeight": 0.040552,
      "pnlUsd": 44.47,
      "returnPct": 13.898
    },
    {
      "ticker": "PLTR",
      "shares": 2.53356972,
      "entryPrice": 157.88,
      "currentPrice": 134.89,
      "entryValue": 400.0,
      "marketValue": 341.75,
      "currentWeight": 0.038024,
      "pnlUsd": -58.25,
      "returnPct": -14.562
    },
    {
      "ticker": "TSM",
      "shares": 1.65744655,
      "entryPrice": 241.3351,
      "currentPrice": 360.39,
      "entryValue": 400.0,
      "marketValue": 597.33,
      "currentWeight": 0.066459,
      "pnlUsd": 197.33,
      "returnPct": 49.332
    },
    {
      "ticker": "AMD",
      "shares": 2.07301619,
      "entryPrice": 173.66,
      "currentPrice": 203.37,
      "entryValue": 360.0,
      "marketValue": 421.59,
      "currentWeight": 0.046906,
      "pnlUsd": 61.59,
      "returnPct": 17.108
    },
    {
      "ticker": "CRWV",
      "shares": 3.26441788,
      "entryPrice": 110.28,
      "currentPrice": 97.14,
      "entryValue": 360.0,
      "marketValue": 317.11,
      "currentWeight": 0.035281,
      "pnlUsd": -42.89,
      "returnPct": -11.915
    },
    {
      "ticker": "ZS",
      "shares": 0.83033488,
      "entryPrice": 289.04,
      "currentPrice": 168.99,
      "entryValue": 240.0,
      "marketValue": 140.32,
      "currentWeight": 0.015612,
      "pnlUsd": -99.68,
      "returnPct": -41.534
    },
    {
      "ticker": "CRM",
      "shares": 1.03955716,
      "entryPrice": 269.3455,
      "currentPrice": 185.29,
      "entryValue": 280.0,
      "marketValue": 192.62,
      "currentWeight": 0.021431,
      "pnlUsd": -87.38,
      "returnPct": -31.207
    },
    {
      "ticker": "GFS",
      "shares": 7.86627329,
      "entryPrice": 40.68,
      "currentPrice": 45.44,
      "entryValue": 320.0,
      "marketValue": 357.44,
      "currentWeight": 0.039769,
      "pnlUsd": 37.44,
      "returnPct": 11.701
    },
    {
      "ticker": "RTX",
      "shares": 2.58441413,
      "entryPrice": 154.774,
      "currentPrice": 205.41,
      "entryValue": 400.0,
      "marketValue": 530.86,
      "currentWeight": 0.059064,
      "pnlUsd": 130.86,
      "returnPct": 32.716
    },
    {
      "ticker": "LMT",
      "shares": 0.57812309,
      "entryPrice": 415.1365,
      "currentPrice": 666.51,
      "entryValue": 240.0,
      "marketValue": 385.32,
      "currentWeight": 0.042871,
      "pnlUsd": 145.32,
      "returnPct": 60.552
    },
    {
      "ticker": "BA",
      "shares": 0.67679031,
      "entryPrice": 236.41,
      "currentPrice": 233.71,
      "entryValue": 160.0,
      "marketValue": 158.17,
      "currentWeight": 0.017598,
      "pnlUsd": -1.83,
      "returnPct": -1.142
    },
    {
      "ticker": "NOC",
      "shares": 0.35454236,
      "entryPrice": 564.1075,
      "currentPrice": 736.87,
      "entryValue": 200.0,
      "marketValue": 261.25,
      "currentWeight": 0.029067,
      "pnlUsd": 61.25,
      "returnPct": 30.626
    },
    {
      "ticker": "GD",
      "shares": 0.77304244,
      "entryPrice": 310.4616,
      "currentPrice": 354.34,
      "entryValue": 240.0,
      "marketValue": 273.92,
      "currentWeight": 0.030476,
      "pnlUsd": 33.92,
      "returnPct": 14.133
    },
    {
      "ticker": "HII",
      "shares": 0.9228788,
      "entryPrice": 260.0558,
      "currentPrice": 443.14,
      "entryValue": 240.0,
      "marketValue": 408.96,
      "currentWeight": 0.045502,
      "pnlUsd": 168.96,
      "returnPct": 70.402
    },
    {
      "ticker": "LHX",
      "shares": 0.74857871,
      "entryPrice": 267.173,
      "currentPrice": 358.7,
      "entryValue": 200.0,
      "marketValue": 268.52,
      "currentWeight": 0.029875,
      "pnlUsd": 68.52,
      "returnPct": 34.258
    },
    {
      "ticker": "LDOS",
      "shares": 1.50339641,
      "entryPrice": 159.6385,
      "currentPrice": 176.27,
      "entryValue": 240.0,
      "marketValue": 265.0,
      "currentWeight": 0.029484,
      "pnlUsd": 25.0,
      "returnPct": 10.418
    },
    {
      "ticker": "CACI",
      "shares": 0.51795582,
      "entryPrice": 463.36,
      "currentPrice": 591.2,
      "entryValue": 240.0,
      "marketValue": 306.22,
      "currentWeight": 0.03407,
      "pnlUsd": 66.22,
      "returnPct": 27.59
    },
    {
      "ticker": "MRCY",
      "shares": 4.54890083,
      "entryPrice": 52.76,
      "currentPrice": 89.86,
      "entryValue": 240.0,
      "marketValue": 408.76,
      "currentWeight": 0.045479,
      "pnlUsd": 168.76,
      "returnPct": 70.318
    }
  ],
  "missingTickersDropped": [],
  "weightsRenormalized": false
}