{
  "asOf": "2026-07-22",
  "entryDateUsed": "2025-07-28",
  "valuationDate": "2026-07-21",
  "initialCapitalUsd": 8000.0,
  "aumUsd": 9956.1,
  "positions": [
    {
      "ticker": "AAPL",
      "shares": 1.87613584,
      "entryPrice": 213.2042,
      "currentPrice": 327.74,
      "entryValue": 400.0,
      "marketValue": 614.88,
      "currentWeight": 0.06176,
      "pnlUsd": 214.88,
      "returnPct": 53.721
    },
    {
      "ticker": "AMZN",
      "shares": 1.54645823,
      "entryPrice": 232.79,
      "currentPrice": 247.55,
      "entryValue": 360.0,
      "marketValue": 382.83,
      "currentWeight": 0.038451,
      "pnlUsd": 22.83,
      "returnPct": 6.34
    },
    {
      "ticker": "MSFT",
      "shares": 0.9440664,
      "entryPrice": 508.4388,
      "currentPrice": 397.75,
      "entryValue": 480.0,
      "marketValue": 375.5,
      "currentWeight": 0.037716,
      "pnlUsd": -104.5,
      "returnPct": -21.77
    },
    {
      "ticker": "GOOGL",
      "shares": 2.08298421,
      "entryPrice": 192.0322,
      "currentPrice": 347.15,
      "entryValue": 400.0,
      "marketValue": 723.11,
      "currentWeight": 0.07263,
      "pnlUsd": 323.11,
      "returnPct": 80.777
    },
    {
      "ticker": "NVDA",
      "shares": 2.71931729,
      "entryPrice": 176.5149,
      "currentPrice": 207.29,
      "entryValue": 480.0,
      "marketValue": 563.69,
      "currentWeight": 0.056617,
      "pnlUsd": 83.69,
      "returnPct": 17.435
    },
    {
      "ticker": "META",
      "shares": 0.67106058,
      "entryPrice": 715.2856,
      "currentPrice": 643.81,
      "entryValue": 480.0,
      "marketValue": 432.04,
      "currentWeight": 0.043394,
      "pnlUsd": -47.96,
      "returnPct": -9.993
    },
    {
      "ticker": "PANW",
      "shares": 1.56479218,
      "entryPrice": 204.5,
      "currentPrice": 342.15,
      "entryValue": 320.0,
      "marketValue": 535.39,
      "currentWeight": 0.053775,
      "pnlUsd": 215.39,
      "returnPct": 67.311
    },
    {
      "ticker": "AVGO",
      "shares": 1.09529287,
      "entryPrice": 292.1593,
      "currentPrice": 386.5,
      "entryValue": 320.0,
      "marketValue": 423.33,
      "currentWeight": 0.04252,
      "pnlUsd": 103.33,
      "returnPct": 32.291
    },
    {
      "ticker": "PLTR",
      "shares": 2.53356972,
      "entryPrice": 157.88,
      "currentPrice": 132.66,
      "entryValue": 400.0,
      "marketValue": 336.1,
      "currentWeight": 0.033759,
      "pnlUsd": -63.9,
      "returnPct": -15.974
    },
    {
      "ticker": "TSM",
      "shares": 1.66600931,
      "entryPrice": 240.0947,
      "currentPrice": 424.61,
      "entryValue": 400.0,
      "marketValue": 707.4,
      "currentWeight": 0.071052,
      "pnlUsd": 307.4,
      "returnPct": 76.851
    },
    {
      "ticker": "AMD",
      "shares": 2.07301619,
      "entryPrice": 173.66,
      "currentPrice": 544.43,
      "entryValue": 360.0,
      "marketValue": 1128.61,
      "currentWeight": 0.113359,
      "pnlUsd": 768.61,
      "returnPct": 213.503
    },
    {
      "ticker": "CRWV",
      "shares": 3.26441788,
      "entryPrice": 110.28,
      "currentPrice": 79.58,
      "entryValue": 360.0,
      "marketValue": 259.78,
      "currentWeight": 0.026093,
      "pnlUsd": -100.22,
      "returnPct": -27.838
    },
    {
      "ticker": "ZS",
      "shares": 0.83033488,
      "entryPrice": 289.04,
      "currentPrice": 148.72,
      "entryValue": 240.0,
      "marketValue": 123.49,
      "currentWeight": 0.012403,
      "pnlUsd": -116.51,
      "returnPct": -48.547
    },
    {
      "ticker": "CRM",
      "shares": 1.04484691,
      "entryPrice": 267.9818,
      "currentPrice": 170.06,
      "entryValue": 280.0,
      "marketValue": 177.69,
      "currentWeight": 0.017847,
      "pnlUsd": -102.31,
      "returnPct": -36.54
    },
    {
      "ticker": "GFS",
      "shares": 7.87760953,
      "entryPrice": 40.6215,
      "currentPrice": 59.39,
      "entryValue": 320.0,
      "marketValue": 467.85,
      "currentWeight": 0.046991,
      "pnlUsd": 147.85,
      "returnPct": 46.204
    },
    {
      "ticker": "RTX",
      "shares": 2.60379926,
      "entryPrice": 153.6217,
      "currentPrice": 193.67,
      "entryValue": 400.0,
      "marketValue": 504.28,
      "currentWeight": 0.05065,
      "pnlUsd": 104.28,
      "returnPct": 26.069
    },
    {
      "ticker": "LMT",
      "shares": 0.58497446,
      "entryPrice": 410.2743,
      "currentPrice": 507.09,
      "entryValue": 240.0,
      "marketValue": 296.63,
      "currentWeight": 0.029794,
      "pnlUsd": 56.63,
      "returnPct": 23.598
    },
    {
      "ticker": "BA",
      "shares": 0.67679031,
      "entryPrice": 236.41,
      "currentPrice": 204.8,
      "entryValue": 160.0,
      "marketValue": 138.61,
      "currentWeight": 0.013922,
      "pnlUsd": -21.39,
      "returnPct": -13.371
    },
    {
      "ticker": "NOC",
      "shares": 0.35724331,
      "entryPrice": 559.8425,
      "currentPrice": 512.29,
      "entryValue": 200.0,
      "marketValue": 183.01,
      "currentWeight": 0.018382,
      "pnlUsd": -16.99,
      "returnPct": -8.494
    },
    {
      "ticker": "GD",
      "shares": 0.78005126,
      "entryPrice": 307.6721,
      "currentPrice": 367.73,
      "entryValue": 240.0,
      "marketValue": 286.85,
      "currentWeight": 0.028811,
      "pnlUsd": 46.85,
      "returnPct": 19.52
    },
    {
      "ticker": "HII",
      "shares": 0.92976098,
      "entryPrice": 258.1309,
      "currentPrice": 268.76,
      "entryValue": 240.0,
      "marketValue": 249.88,
      "currentWeight": 0.025098,
      "pnlUsd": 9.88,
      "returnPct": 4.118
    },
    {
      "ticker": "LHX",
      "shares": 0.75422962,
      "entryPrice": 265.1712,
      "currentPrice": 277.71,
      "entryValue": 200.0,
      "marketValue": 209.46,
      "currentWeight": 0.021038,
      "pnlUsd": 9.46,
      "returnPct": 4.729
    },
    {
      "ticker": "LDOS",
      "shares": 1.51244762,
      "entryPrice": 158.6832,
      "currentPrice": 104.92,
      "entryValue": 240.0,
      "marketValue": 158.69,
      "currentWeight": 0.015939,
      "pnlUsd": -81.31,
      "returnPct": -33.881
    },
    {
      "ticker": "CACI",
      "shares": 0.51795582,
      "entryPrice": 463.36,
      "currentPrice": 440.76,
      "entryValue": 240.0,
      "marketValue": 228.29,
      "currentWeight": 0.02293,
      "pnlUsd": -11.71,
      "returnPct": -4.877
    },
    {
      "ticker": "MRCY",
      "shares": 4.54890083,
      "entryPrice": 52.76,
      "currentPrice": 98.64,
      "entryValue": 240.0,
      "marketValue": 448.7,
      "currentWeight": 0.045068,
      "pnlUsd": 208.7,
      "returnPct": 86.96
    }
  ],
  "missingTickersDropped": [],
  "weightsRenormalized": false
}